nsj_embedding_search/__init__.py
nsj_embedding_search/dao.py
nsj_embedding_search/embedding_util.py
nsj_embedding_search/enums.py
nsj_embedding_search/search_result.py
nsj_embedding_search/semantic_search.py
nsj_embedding_search/settings.py
nsj_embedding_search/text_utils.py
nsj_embedding_search-0.1.0.dist-info/METADATA
nsj_embedding_search-0.1.0.dist-info/WHEEL
nsj_embedding_search-0.1.0.dist-info/top_level.txt
nsj_embedding_search-0.1.0.dist-info/RECORD
