Metadata-Version: 2.4
Name: nsj_embedding_search
Version: 0.1.0
Summary: Biblioteca python para simplificar a implementação de mecanismos de indexação e busca contextual, por meio da técnica de IA denominada text embedding.
Home-page: https://github.com/Nasajon/nsj-embedding-search
Author: Nasajon Sistemas
Author-email: contact.dev@nasajon.com.br
Project-URL: Source, https://github.com/Nasajon/nsj-embedding-search
Classifier: Development Status :: 3 - Alpha
Classifier: Intended Audience :: Developers
Classifier: Topic :: Software Development :: Libraries
Classifier: Programming Language :: Python :: 3
Requires-Python: >=3.4
Requires-Dist: nsj_sql_utils_lib<3.0.0,>=2.0.2
Requires-Dist: openai<2.0.0,>=1.57.2
Requires-Dist: tiktoken<1.0.0,>=0.7.0
Requires-Dist: numpy<3.0.0,>=2.2.6
Requires-Dist: sortedcontainers<3.0.0,>=2.4.0
